README.rst
setup.py
PyMultition/__init__.py
PyMultition/pymultition.py
PyMultition.egg-info/PKG-INFO
PyMultition.egg-info/SOURCES.txt
PyMultition.egg-info/dependency_links.txt
PyMultition.egg-info/top_level.txt